cbssa/__init__.py
cbssa/bayesian.py
cbssa/data_binning.py
cbssa/football.py
cbssa/legacy.py
cbssa/linear_regression.py
cbssa/logistic_regression.py
cbssa/model_evaluation.py
cbssa/scrape.py
cbssa/simple_rating_system.py
cbssa/utils.py
cbssa-0.0.7.dist-info/METADATA
cbssa-0.0.7.dist-info/WHEEL
cbssa-0.0.7.dist-info/licenses/LICENSE
cbssa-0.0.7.dist-info/RECORD
