Metadata-Version: 2.1
Name: cbssa
Version: 0.0.7
Summary: Columbia Business School Sports Analytics
Project-URL: Homepage, https://github.com/pr/cbssa
Project-URL: Bug Tracker, https://github.com/pr/cbssa/issues
Author-email: Columbia Business School <peter@peter.net>
License-File: LICENSE
Classifier: License :: OSI Approved :: MIT License
Classifier: Operating System :: OS Independent
Classifier: Programming Language :: Python :: 3
Requires-Python: >=3.10
Requires-Dist: matplotlib
Requires-Dist: numpy
Requires-Dist: pandas
Requires-Dist: scipy
Requires-Dist: statsmodels
